{
	"dataTime": "2023-03-21",
	"daily": {
		"dataTime": "2023-03-21",
		"firstCnt": "68",
		"secondCnt": "89",
		"thirdCnt": "0",
		"fourCnt": "0",
		"winCnt": "4798",
		"vrate": "0%",
		"wrate": "0%"
	},
	"yesterday": {
		"dataTime": "2023-03-20",
		"firstCnt": "44827925",
		"secondCnt": "44412381",
		"thirdCnt": "33479417",
		"fourCnt": "7516147",
		"winCnt": "6572688",
		"vrate": "0%",
		"wrate": "0%"
	},
	"today": {
		"dataTime": "2023-03-21",
		"firstCnt": "44827993",
		"secondCnt": "44412470",
		"thirdCnt": "33479417",
		"fourCnt": "7516147",
		"winCnt": "6577486",
		"vrate": "86.8%",
		"wrate": "14%"
	}
}