{
	"dataTime": "2022-04-08",
	"서울특별시": {
		"firstCnt": "337",
		"firstTot": "8324499",
		"secondCnt": "341",
		"secondTot": "8238419",
		"thirdCnt": "3614",
		"thirdTot": "5924087",
		"fourCnt": "703",
		"fourTot": "37878"
	},
	"부산광역시": {
		"firstCnt": "108",
		"firstTot": "2874717",
		"secondCnt": "113",
		"secondTot": "2843467",
		"thirdCnt": "911",
		"thirdTot": "2091736",
		"fourCnt": "251",
		"fourTot": "16582"
	},
	"대구광역시": {
		"firstCnt": "74",
		"firstTot": "2016456",
		"secondCnt": "89",
		"secondTot": "1991836",
		"thirdCnt": "781",
		"thirdTot": "1375681",
		"fourCnt": "154",
		"fourTot": "9899"
	},
	"인천광역시": {
		"firstCnt": "106",
		"firstTot": "2561481",
		"secondCnt": "90",
		"secondTot": "2534860",
		"thirdCnt": "1132",
		"thirdTot": "1867477",
		"fourCnt": "275",
		"fourTot": "14030"
	},
	"광주광역시": {
		"firstCnt": "62",
		"firstTot": "1260052",
		"secondCnt": "56",
		"secondTot": "1247240",
		"thirdCnt": "656",
		"thirdTot": "949163",
		"fourCnt": "66",
		"fourTot": "12315"
	},
	"대전광역시": {
		"firstCnt": "76",
		"firstTot": "1243774",
		"secondCnt": "52",
		"secondTot": "1230346",
		"thirdCnt": "686",
		"thirdTot": "889294",
		"fourCnt": "80",
		"fourTot": "8214"
	},
	"울산광역시": {
		"firstCnt": "93",
		"firstTot": "966800",
		"secondCnt": "53",
		"secondTot": "956477",
		"thirdCnt": "589",
		"thirdTot": "705502",
		"fourCnt": "59",
		"fourTot": "5078"
	},
	"세종특별자치시": {
		"firstCnt": "22",
		"firstTot": "296734",
		"secondCnt": "11",
		"secondTot": "292594",
		"thirdCnt": "173",
		"thirdTot": "203677",
		"fourCnt": "18",
		"fourTot": "1406"
	},
	"경기도": {
		"firstCnt": "571",
		"firstTot": "11790087",
		"secondCnt": "477",
		"secondTot": "11664260",
		"thirdCnt": "4864",
		"thirdTot": "8494429",
		"fourCnt": "1165",
		"fourTot": "71519"
	},
	"강원도": {
		"firstCnt": "113",
		"firstTot": "1345741",
		"secondCnt": "59",
		"secondTot": "1333054",
		"thirdCnt": "686",
		"thirdTot": "1041000",
		"fourCnt": "178",
		"fourTot": "9914"
	},
	"충청북도": {
		"firstCnt": "97",
		"firstTot": "1424230",
		"secondCnt": "49",
		"secondTot": "1410218",
		"thirdCnt": "748",
		"thirdTot": "1082082",
		"fourCnt": "312",
		"fourTot": "12753"
	},
	"충청남도": {
		"firstCnt": "113",
		"firstTot": "1892220",
		"secondCnt": "87",
		"secondTot": "1872683",
		"thirdCnt": "829",
		"thirdTot": "1444813",
		"fourCnt": "225",
		"fourTot": "16482"
	},
	"전라북도": {
		"firstCnt": "215",
		"firstTot": "1588651",
		"secondCnt": "86",
		"secondTot": "1573728",
		"thirdCnt": "967",
		"thirdTot": "1258859",
		"fourCnt": "167",
		"fourTot": "20438"
	},
	"전라남도": {
		"firstCnt": "144",
		"firstTot": "1648065",
		"secondCnt": "64",
		"secondTot": "1631701",
		"thirdCnt": "952",
		"thirdTot": "1335057",
		"fourCnt": "271",
		"fourTot": "28126"
	},
	"경상북도": {
		"firstCnt": "149",
		"firstTot": "2287445",
		"secondCnt": "112",
		"secondTot": "2261280",
		"thirdCnt": "912",
		"thirdTot": "1690356",
		"fourCnt": "154",
		"fourTot": "16739"
	},
	"경상남도": {
		"firstCnt": "152",
		"firstTot": "2876581",
		"secondCnt": "106",
		"secondTot": "2844566",
		"thirdCnt": "1180",
		"thirdTot": "2097953",
		"fourCnt": "351",
		"fourTot": "18925"
	},
	"제주특별자치도": {
		"firstCnt": "41",
		"firstTot": "588427",
		"secondCnt": "26",
		"secondTot": "581974",
		"thirdCnt": "308",
		"thirdTot": "427286",
		"fourCnt": "95",
		"fourTot": "3946"
	}
}