{
  "dataTime": "2022-01-23",
  "daily": {
    "dataTime": "2022-01-23",
    "firstCnt": "9349",
    "secondCnt": "17952",
    "thirdCnt": "258013"
  },
  "yesterday": {
    "dataTime": "2022-01-22",
    "firstCnt": "44559381",
    "secondCnt": "43783899",
    "thirdCnt": "24974591"
  },
  "today": {
    "dataTime": "2022-01-23",
    "firstCnt": "44568730",
    "secondCnt": "43801851",
    "thirdCnt": "25232604"
  },
  "60세이상 접종률": {
    "firstCnt": "96",
    "secondCnt": "95.2",
    "thirdCnt": "84.7"
  }
}