{
	"dataTime": "2022-07-20",
	"서울특별시": {
		"firstCnt": "92",
		"firstTot": "8338117",
		"secondCnt": "95",
		"secondTot": "8259138",
		"thirdCnt": "859",
		"thirdTot": "6025028",
		"fourCnt": "12124",
		"fourTot": "777975"
	},
	"부산광역시": {
		"firstCnt": "18",
		"firstTot": "2878968",
		"secondCnt": "21",
		"secondTot": "2850116",
		"thirdCnt": "238",
		"thirdTot": "2124977",
		"fourCnt": "5020",
		"fourTot": "329797"
	},
	"대구광역시": {
		"firstCnt": "24",
		"firstTot": "2018847",
		"secondCnt": "20",
		"secondTot": "1995939",
		"thirdCnt": "174",
		"thirdTot": "1397065",
		"fourCnt": "3462",
		"fourTot": "167905"
	},
	"인천광역시": {
		"firstCnt": "27",
		"firstTot": "2567966",
		"secondCnt": "14",
		"secondTot": "2543542",
		"thirdCnt": "219",
		"thirdTot": "1897956",
		"fourCnt": "3414",
		"fourTot": "254099"
	},
	"광주광역시": {
		"firstCnt": "17",
		"firstTot": "1262267",
		"secondCnt": "9",
		"secondTot": "1250700",
		"thirdCnt": "97",
		"thirdTot": "964105",
		"fourCnt": "2681",
		"fourTot": "154103"
	},
	"대전광역시": {
		"firstCnt": "15",
		"firstTot": "1245826",
		"secondCnt": "8",
		"secondTot": "1233619",
		"thirdCnt": "91",
		"thirdTot": "903778",
		"fourCnt": "1828",
		"fourTot": "127439"
	},
	"울산광역시": {
		"firstCnt": "6",
		"firstTot": "968215",
		"secondCnt": "5",
		"secondTot": "958856",
		"thirdCnt": "87",
		"thirdTot": "716825",
		"fourCnt": "1338",
		"fourTot": "78208"
	},
	"세종특별자치시": {
		"firstCnt": "2",
		"firstTot": "298044",
		"secondCnt": "4",
		"secondTot": "294271",
		"thirdCnt": "14",
		"thirdTot": "207819",
		"fourCnt": "330",
		"fourTot": "22182"
	},
	"경기도": {
		"firstCnt": "119",
		"firstTot": "11817356",
		"secondCnt": "104",
		"secondTot": "11702052",
		"thirdCnt": "992",
		"thirdTot": "8632692",
		"fourCnt": "15754",
		"fourTot": "1044751"
	},
	"강원도": {
		"firstCnt": "13",
		"firstTot": "1348814",
		"secondCnt": "11",
		"secondTot": "1337545",
		"thirdCnt": "79",
		"thirdTot": "1057285",
		"fourCnt": "2451",
		"fourTot": "182217"
	},
	"충청북도": {
		"firstCnt": "9",
		"firstTot": "1427475",
		"secondCnt": "13",
		"secondTot": "1414895",
		"thirdCnt": "99",
		"thirdTot": "1100340",
		"fourCnt": "2506",
		"fourTot": "191266"
	},
	"충청남도": {
		"firstCnt": "18",
		"firstTot": "1897418",
		"secondCnt": "26",
		"secondTot": "1879916",
		"thirdCnt": "111",
		"thirdTot": "1468812",
		"fourCnt": "2889",
		"fourTot": "248566"
	},
	"전라북도": {
		"firstCnt": "18",
		"firstTot": "1592420",
		"secondCnt": "18",
		"secondTot": "1579293",
		"thirdCnt": "132",
		"thirdTot": "1278878",
		"fourCnt": "4067",
		"fourTot": "266380"
	},
	"전라남도": {
		"firstCnt": "13",
		"firstTot": "1652832",
		"secondCnt": "17",
		"secondTot": "1638169",
		"thirdCnt": "171",
		"thirdTot": "1357217",
		"fourCnt": "3914",
		"fourTot": "331373"
	},
	"경상북도": {
		"firstCnt": "22",
		"firstTot": "2291594",
		"secondCnt": "16",
		"secondTot": "2267749",
		"thirdCnt": "175",
		"thirdTot": "1717009",
		"fourCnt": "4195",
		"fourTot": "257458"
	},
	"경상남도": {
		"firstCnt": "21",
		"firstTot": "2881707",
		"secondCnt": "25",
		"secondTot": "2852394",
		"thirdCnt": "264",
		"thirdTot": "2132840",
		"fourCnt": "5423",
		"fourTot": "328790"
	},
	"제주특별자치도": {
		"firstCnt": "8",
		"firstTot": "590023",
		"secondCnt": "5",
		"secondTot": "584331",
		"thirdCnt": "85",
		"thirdTot": "435556",
		"fourCnt": "1270",
		"fourTot": "61725"
	}
}