{
	"dataTime": "2023-08-17",
	"counter": {
		"dataTime": "2023-08-17",
		"confirmed": "34031503",
		"deaths": "35600",
		"recovered": "0"
	},
	"country": {
		"Nation-wide": {
			"confirmed": "34031503",
			"deaths": "35600",
			"recovered": "0"
		},
		"Seoul": {
			"confirmed": "6652222",
			"deaths": "6632",
			"recovered": "0"
		},
		"Busan": {
			"confirmed": "2065985",
			"deaths": "2923",
			"recovered": "0"
		},
		"Daegu": {
			"confirmed": "1490715",
			"deaths": "2060",
			"recovered": "0"
		},
		"Incheon": {
			"confirmed": "1957463",
			"deaths": "1959",
			"recovered": "0"
		},
		"Gwangju": {
			"confirmed": "1001294",
			"deaths": "856",
			"recovered": "0"
		},
		"Daejeon": {
			"confirmed": "996347",
			"deaths": "986",
			"recovered": "0"
		},
		"Ulsan": {
			"confirmed": "727503",
			"deaths": "543",
			"recovered": "0"
		},
		"Sejong": {
			"confirmed": "268719",
			"deaths": "58",
			"recovered": "0"
		},
		"Gyeonggi-do": {
			"confirmed": "9122771",
			"deaths": "8576",
			"recovered": "0"
		},
		"Gangwon-do": {
			"confirmed": "988403",
			"deaths": "1385",
			"recovered": "0"
		},
		"Chungcheongbuk-do": {
			"confirmed": "1056899",
			"deaths": "1086",
			"recovered": "0"
		},
		"Chungcheongnam-do": {
			"confirmed": "1366767",
			"deaths": "1635",
			"recovered": "0"
		},
		"Jeollabuk-do": {
			"confirmed": "1145384",
			"deaths": "1268",
			"recovered": "0"
		},
		"Jeollanam-do": {
			"confirmed": "1124472",
			"deaths": "1068",
			"recovered": "0"
		},
		"Gyeongsangbuk-do": {
			"confirmed": "1554249",
			"deaths": "2161",
			"recovered": "0"
		},
		"Gyeongsangnam-do": {
			"confirmed": "2047077",
			"deaths": "2073",
			"recovered": "0"
		},
		"Jeju": {
			"confirmed": "446358",
			"deaths": "315",
			"recovered": "0"
		},
		"Lazaretto": {
			"confirmed": "18875",
			"deaths": "16",
			"recovered": "0"
		}
	}
}