{
  "counter": {
    "dataTime": "2022-01-21",
    "daily": {
      "dataTime": "2022-01-21",
      "firstCnt": "10273",
      "secondCnt": "43941",
      "thirdCnt": "277176"
    },
    "yesterday": {
      "dataTime": "2022-01-20",
      "firstCnt": "44532026",
      "secondCnt": "43678627",
      "thirdCnt": "24222950"
    },
    "today": {
      "dataTime": "2022-01-21",
      "firstCnt": "44542299",
      "secondCnt": "43722568",
      "thirdCnt": "24500126"
    },
    "60세이상 접종률": {
      "firstCnt": "96",
      "secondCnt": "95.2",
      "thirdCnt": "84.3"
    }
  },
  "country": {
    "dataTime": "2022-01-21",
    "서울특별시": {
      "firstCnt": "1480",
      "firstTot": "8244897",
      "secondCnt": "5848",
      "secondTot": "8109394",
      "thirdCnt": "51967",
      "thirdTot": "4438807"
    },
    "부산광역시": {
      "firstCnt": "597",
      "firstTot": "2851081",
      "secondCnt": "2772",
      "secondTot": "2797142",
      "thirdCnt": "14437",
      "thirdTot": "1597142"
    },
    "대구광역시": {
      "firstCnt": "532",
      "firstTot": "1999072",
      "secondCnt": "2542",
      "secondTot": "1954015",
      "thirdCnt": "10708",
      "thirdTot": "1009243"
    },
    "인천광역시": {
      "firstCnt": "598",
      "firstTot": "2535099",
      "secondCnt": "2143",
      "secondTot": "2491039",
      "thirdCnt": "16164",
      "thirdTot": "1375168"
    },
    "광주광역시": {
      "firstCnt": "296",
      "firstTot": "1248827",
      "secondCnt": "1591",
      "secondTot": "1225534",
      "thirdCnt": "7604",
      "thirdTot": "704447"
    },
    "대전광역시": {
      "firstCnt": "300",
      "firstTot": "1232446",
      "secondCnt": "1386",
      "secondTot": "1208110",
      "thirdCnt": "8024",
      "thirdTot": "649743"
    },
    "울산광역시": {
      "firstCnt": "325",
      "firstTot": "957766",
      "secondCnt": "1487",
      "secondTot": "937685",
      "thirdCnt": "7797",
      "thirdTot": "496101"
    },
    "세종특별자치시": {
      "firstCnt": "101",
      "firstTot": "290836",
      "secondCnt": "397",
      "secondTot": "283883",
      "thirdCnt": "2002",
      "thirdTot": "142843"
    },
    "경기도": {
      "firstCnt": "2669",
      "firstTot": "11663218",
      "secondCnt": "11076",
      "secondTot": "11449473",
      "thirdCnt": "75114",
      "thirdTot": "6175184"
    },
    "강원도": {
      "firstCnt": "321",
      "firstTot": "1333094",
      "secondCnt": "1272",
      "secondTot": "1310806",
      "thirdCnt": "8128",
      "thirdTot": "819435"
    },
    "충청북도": {
      "firstCnt": "330",
      "firstTot": "1409960",
      "secondCnt": "1688",
      "secondTot": "1384838",
      "thirdCnt": "9662",
      "thirdTot": "808834"
    },
    "충청남도": {
      "firstCnt": "478",
      "firstTot": "1871989",
      "secondCnt": "1932",
      "secondTot": "1836719",
      "thirdCnt": "12352",
      "thirdTot": "1082778"
    },
    "전라북도": {
      "firstCnt": "266",
      "firstTot": "1575688",
      "secondCnt": "1405",
      "secondTot": "1551531",
      "thirdCnt": "9583",
      "thirdTot": "984592"
    },
    "전라남도": {
      "firstCnt": "399",
      "firstTot": "1633507",
      "secondCnt": "1342",
      "secondTot": "1606771",
      "thirdCnt": "9561",
      "thirdTot": "1059746"
    },
    "경상북도": {
      "firstCnt": "716",
      "firstTot": "2263275",
      "secondCnt": "3300",
      "secondTot": "2212954",
      "thirdCnt": "13825",
      "thirdTot": "1286475"
    },
    "경상남도": {
      "firstCnt": "713",
      "firstTot": "2850433",
      "secondCnt": "3025",
      "secondTot": "2793509",
      "thirdCnt": "16805",
      "thirdTot": "1563579"
    },
    "제주특별자치도": {
      "firstCnt": "152",
      "firstTot": "581111",
      "secondCnt": "735",
      "secondTot": "569165",
      "thirdCnt": "3443",
      "thirdTot": "306009"
    }
  }
}