{
	"dataTime": "2024-02-20",
	"counter": {
		"dataTime": "2024-02-20",
		"daily": {
			"dataTime": "2024-02-20",
			"vcnCnt": "1152",
			"vrate": "0%"
		},
		"yesterday": {
			"dataTime": "2024-02-19",
			"vcnCnt": "4923128",
			"vrate": "0%"
		},
		"today": {
			"dataTime": "2024-02-20",
			"vcnCnt": "4924280",
			"vrate": "9.9%"
		}
	},
	"country": {
		"dataTime": "2024-02-20",
		"서울특별시": {
			"vcnCnt": "126",
			"vcnTot": "707109",
			"vrate": "40.8%"
		},
		"부산광역시": {
			"vcnCnt": "84",
			"vcnTot": "282117",
			"vrate": "37.7%"
		},
		"대구광역시": {
			"vcnCnt": "20",
			"vcnTot": "155826",
			"vrate": "33.2%"
		},
		"인천광역시": {
			"vcnCnt": "26",
			"vcnTot": "204113",
			"vrate": "40.9%"
		},
		"광주광역시": {
			"vcnCnt": "7",
			"vcnTot": "111734",
			"vrate": "47.5%"
		},
		"대전광역시": {
			"vcnCnt": "9",
			"vcnTot": "105652",
			"vrate": "42.9%"
		},
		"울산광역시": {
			"vcnCnt": "7",
			"vcnTot": "68888",
			"vrate": "39%"
		},
		"세종특별자치시": {
			"vcnCnt": "2",
			"vcnTot": "18838",
			"vrate": "44%"
		},
		"경기도": {
			"vcnCnt": "142",
			"vcnTot": "887753",
			"vrate": "41.7%"
		},
		"충청북도": {
			"vcnCnt": "14",
			"vcnTot": "145691",
			"vrate": "43.5%"
		},
		"충청남도": {
			"vcnCnt": "34",
			"vcnTot": "194510",
			"vrate": "42.5%"
		},
		"전라남도": {
			"vcnCnt": "8",
			"vcnTot": "232842",
			"vrate": "49.1%"
		},
		"경상북도": {
			"vcnCnt": "37",
			"vcnTot": "243674",
			"vrate": "38.4%"
		},
		"경상남도": {
			"vcnCnt": "72",
			"vcnTot": "256568",
			"vrate": "38.1%"
		},
		"제주특별자치도": {
			"vcnCnt": "3",
			"vcnTot": "46682",
			"vrate": "38.5%"
		},
		"강원특별자치도": {
			"vcnCnt": "76",
			"vcnTot": "146068",
			"vrate": "39.7%"
		},
		"전북특별자치도": {
			"vcnCnt": "26",
			"vcnTot": "201342",
			"vrate": "47.4%"
		}
	}
}