{
	"dataTime": "2023-02-07",
	"counter": {
		"dataTime": "2023-02-07",
		"daily": {
			"dataTime": "2023-02-07",
			"firstCnt": "145",
			"secondCnt": "221",
			"thirdCnt": "0",
			"fourCnt": "0",
			"winCnt": "16596",
			"vrate": "0%",
			"wrate": "0%"
		},
		"yesterday": {
			"dataTime": "2023-02-06",
			"firstCnt": "44850058",
			"secondCnt": "44432723",
			"thirdCnt": "33503588",
			"fourCnt": "7529115",
			"winCnt": "6209553",
			"vrate": "0%",
			"wrate": "0%"
		},
		"today": {
			"dataTime": "2023-02-07",
			"firstCnt": "44850203",
			"secondCnt": "44432944",
			"thirdCnt": "33503588",
			"fourCnt": "7529115",
			"winCnt": "6226149",
			"vrate": "88.7%",
			"wrate": "13.2%"
		}
	},
	"country": {
		"dataTime": "2023-02-07",
		"서울특별시": {
			"firstCnt": "24",
			"firstTot": "8298041",
			"secondCnt": "50",
			"secondTot": "8222617",
			"thirdCnt": "0",
			"thirdTot": "6058912",
			"fourCnt": "0",
			"fourTot": "1263261",
			"winCnt": "3400",
			"winTot": "1145287",
			"vrate": "89.6%",
			"wrate": "13.1%",
			"frate": "90.4%"
		},
		"부산광역시": {
			"firstCnt": "9",
			"firstTot": "2863336",
			"secondCnt": "14",
			"secondTot": "2835657",
			"thirdCnt": "0",
			"thirdTot": "2130597",
			"fourCnt": "0",
			"fourTot": "500115",
			"winCnt": "997",
			"winTot": "408004",
			"vrate": "87%",
			"wrate": "13.2%",
			"frate": "87.9%"
		},
		"대구광역시": {
			"firstCnt": "6",
			"firstTot": "2005978",
			"secondCnt": "7",
			"secondTot": "1983752",
			"thirdCnt": "0",
			"thirdTot": "1397609",
			"fourCnt": "0",
			"fourTot": "265579",
			"winCnt": "612",
			"winTot": "243863",
			"vrate": "85.5%",
			"wrate": "11.2%",
			"frate": "86.5%"
		},
		"인천광역시": {
			"firstCnt": "13",
			"firstTot": "2563413",
			"secondCnt": "13",
			"secondTot": "2539807",
			"thirdCnt": "0",
			"thirdTot": "1909487",
			"fourCnt": "0",
			"fourTot": "407305",
			"winCnt": "920",
			"winTot": "315553",
			"vrate": "88.5%",
			"wrate": "11.7%",
			"frate": "89.3%"
		},
		"광주광역시": {
			"firstCnt": "7",
			"firstTot": "1254970",
			"secondCnt": "2",
			"secondTot": "1243885",
			"thirdCnt": "0",
			"thirdTot": "963873",
			"fourCnt": "0",
			"fourTot": "240134",
			"winCnt": "326",
			"winTot": "169314",
			"vrate": "88.8%",
			"wrate": "12.9%",
			"frate": "89.6%"
		},
		"대전광역시": {
			"firstCnt": "3",
			"firstTot": "1239536",
			"secondCnt": "4",
			"secondTot": "1227693",
			"thirdCnt": "0",
			"thirdTot": "905343",
			"fourCnt": "0",
			"fourTot": "197248",
			"winCnt": "370",
			"winTot": "170996",
			"vrate": "87%",
			"wrate": "12.9%",
			"frate": "87.8%"
		},
		"울산광역시": {
			"firstCnt": "4",
			"firstTot": "963575",
			"secondCnt": "5",
			"secondTot": "954546",
			"thirdCnt": "0",
			"thirdTot": "717698",
			"fourCnt": "0",
			"fourTot": "138464",
			"winCnt": "465",
			"winTot": "112649",
			"vrate": "87.5%",
			"wrate": "11.1%",
			"frate": "88.3%"
		},
		"세종특별자치시": {
			"firstCnt": "0",
			"firstTot": "300166",
			"secondCnt": "4",
			"secondTot": "296497",
			"thirdCnt": "0",
			"thirdTot": "210772",
			"fourCnt": "0",
			"fourTot": "35523",
			"winCnt": "98",
			"winTot": "35053",
			"vrate": "81.9%",
			"wrate": "10.8%",
			"frate": "82.9%"
		},
		"경기도": {
			"firstCnt": "48",
			"firstTot": "11789518",
			"secondCnt": "61",
			"secondTot": "11678305",
			"thirdCnt": "0",
			"thirdTot": "8682653",
			"fourCnt": "0",
			"fourTot": "1737890",
			"winCnt": "4457",
			"winTot": "1484589",
			"vrate": "88.7%",
			"wrate": "12.1%",
			"frate": "89.6%"
		},
		"강원도": {
			"firstCnt": "3",
			"firstTot": "1342225",
			"secondCnt": "4",
			"secondTot": "1331439",
			"thirdCnt": "0",
			"thirdTot": "1058319",
			"fourCnt": "0",
			"fourTot": "274784",
			"winCnt": "432",
			"winTot": "208340",
			"vrate": "88.9%",
			"wrate": "14.7%",
			"frate": "89.7%"
		},
		"충청북도": {
			"firstCnt": "3",
			"firstTot": "1420645",
			"secondCnt": "4",
			"secondTot": "1408660",
			"thirdCnt": "0",
			"thirdTot": "1100886",
			"fourCnt": "0",
			"fourTot": "281904",
			"winCnt": "478",
			"winTot": "220430",
			"vrate": "90.6%",
			"wrate": "15.1%",
			"frate": "91.4%"
		},
		"충청남도": {
			"firstCnt": "4",
			"firstTot": "1890068",
			"secondCnt": "8",
			"secondTot": "1873282",
			"thirdCnt": "0",
			"thirdTot": "1471352",
			"fourCnt": "0",
			"fourTot": "374257",
			"winCnt": "702",
			"winTot": "301265",
			"vrate": "90.8%",
			"wrate": "15.6%",
			"frate": "91.6%"
		},
		"전라북도": {
			"firstCnt": "2",
			"firstTot": "1567744",
			"secondCnt": "5",
			"secondTot": "1555617",
			"thirdCnt": "0",
			"thirdTot": "1267720",
			"fourCnt": "0",
			"fourTot": "374443",
			"winCnt": "549",
			"winTot": "285712",
			"vrate": "90.2%",
			"wrate": "17.5%",
			"frate": "90.9%"
		},
		"전라남도": {
			"firstCnt": "6",
			"firstTot": "1639641",
			"secondCnt": "12",
			"secondTot": "1626048",
			"thirdCnt": "0",
			"thirdTot": "1352441",
			"fourCnt": "0",
			"fourTot": "446754",
			"winCnt": "589",
			"winTot": "326419",
			"vrate": "91.3%",
			"wrate": "19.4%",
			"frate": "92%"
		},
		"경상북도": {
			"firstCnt": "5",
			"firstTot": "2273801",
			"secondCnt": "10",
			"secondTot": "2250979",
			"thirdCnt": "0",
			"thirdTot": "1713883",
			"fourCnt": "0",
			"fourTot": "402698",
			"winCnt": "935",
			"winTot": "348600",
			"vrate": "88.3%",
			"wrate": "14.5%",
			"frate": "89.2%"
		},
		"경상남도": {
			"firstCnt": "6",
			"firstTot": "2849216",
			"secondCnt": "13",
			"secondTot": "2821279",
			"thirdCnt": "0",
			"thirdTot": "2124531",
			"fourCnt": "0",
			"fourTot": "494259",
			"winCnt": "1095",
			"winTot": "367447",
			"vrate": "88%",
			"wrate": "12.2%",
			"frate": "88.9%"
		},
		"제주특별자치도": {
			"firstCnt": "2",
			"firstTot": "588330",
			"secondCnt": "5",
			"secondTot": "582881",
			"thirdCnt": "0",
			"thirdTot": "437512",
			"fourCnt": "0",
			"fourTot": "94497",
			"winCnt": "171",
			"winTot": "82628",
			"vrate": "88.8%",
			"wrate": "13.5%",
			"frate": "89.6%"
		}
	}
}