{
	"dataTime": "2022-08-28",
	"Nation-wide": {
		"confirmed": "22983818",
		"deaths": "26569",
		"recovered": "0"
	},
	"Seoul": {
		"confirmed": "4518888",
		"deaths": "5202",
		"recovered": "0"
	},
	"Busan": {
		"confirmed": "1383537",
		"deaths": "2350",
		"recovered": "0"
	},
	"Daegu": {
		"confirmed": "983019",
		"deaths": "1451",
		"recovered": "0"
	},
	"Incheon": {
		"confirmed": "1323390",
		"deaths": "1475",
		"recovered": "0"
	},
	"Gwangju": {
		"confirmed": "679145",
		"deaths": "611",
		"recovered": "0"
	},
	"Daejeon": {
		"confirmed": "661769",
		"deaths": "766",
		"recovered": "0"
	},
	"Ulsan": {
		"confirmed": "501346",
		"deaths": "376",
		"recovered": "0"
	},
	"Sejong": {
		"confirmed": "178223",
		"deaths": "43",
		"recovered": "0"
	},
	"Gyeonggi-do": {
		"confirmed": "6177081",
		"deaths": "6760",
		"recovered": "0"
	},
	"Gangwon-do": {
		"confirmed": "670024",
		"deaths": "954",
		"recovered": "0"
	},
	"Chungcheongbuk-do": {
		"confirmed": "712399",
		"deaths": "806",
		"recovered": "0"
	},
	"Chungcheongnam-do": {
		"confirmed": "919178",
		"deaths": "1094",
		"recovered": "0"
	},
	"Jeollabuk-do": {
		"confirmed": "774861",
		"deaths": "936",
		"recovered": "0"
	},
	"Jeollanam-do": {
		"confirmed": "763474",
		"deaths": "596",
		"recovered": "0"
	},
	"Gyeongsangbuk-do": {
		"confirmed": "1023351",
		"deaths": "1543",
		"recovered": "0"
	},
	"Gyeongsangnam-do": {
		"confirmed": "1383728",
		"deaths": "1383",
		"recovered": "0"
	},
	"Jeju": {
		"confirmed": "317678",
		"deaths": "207",
		"recovered": "0"
	},
	"Lazaretto": {
		"confirmed": "12727",
		"deaths": "16",
		"recovered": "0"
	}
}