{
  "counter": {
    "dataTime": "2021-11-26",
    "confirmed": 432901,
    "deaths": 3440,
    "recovered": 383551
  },
  "country": {
    "dataTime": "2021-11-26",
    "全国": {
      "confirmed": 432901,
      "deaths": 3440,
      "recovered": 383551
    },
    "首尔": {
      "confirmed": 148147,
      "deaths": 1025,
      "recovered": 126661
    },
    "釜山": {
      "confirmed": 15778,
      "deaths": 179,
      "recovered": 14530
    },
    "大邱": {
      "confirmed": 18610,
      "deaths": 305,
      "recovered": 17627
    },
    "仁川": {
      "confirmed": 23627,
      "deaths": 137,
      "recovered": 20663
    },
    "光州": {
      "confirmed": 6085,
      "deaths": 30,
      "recovered": 5644
    },
    "大田": {
      "confirmed": 8378,
      "deaths": 60,
      "recovered": 7810
    },
    "蔚山": {
      "confirmed": 5624,
      "deaths": 57,
      "recovered": 5476
    },
    "世宗": {
      "confirmed": 1507,
      "deaths": 2,
      "recovered": 1406
    },
    "京畿": {
      "confirmed": 129456,
      "deaths": 1131,
      "recovered": 113517
    },
    "江原": {
      "confirmed": 8344,
      "deaths": 71,
      "recovered": 7583
    },
    "忠北": {
      "confirmed": 8689,
      "deaths": 90,
      "recovered": 8312
    },
    "忠南": {
      "confirmed": 12597,
      "deaths": 76,
      "recovered": 11381
    },
    "全北": {
      "confirmed": 6138,
      "deaths": 72,
      "recovered": 5653
    },
    "全南": {
      "confirmed": 4294,
      "deaths": 25,
      "recovered": 3826
    },
    "庆北": {
      "confirmed": 10934,
      "deaths": 103,
      "recovered": 10196
    },
    "庆南": {
      "confirmed": 14694,
      "deaths": 52,
      "recovered": 13691
    },
    "济州": {
      "confirmed": 3576,
      "deaths": 9,
      "recovered": 3310
    },
    "隔離區": {
      "confirmed": 6423,
      "deaths": 16,
      "recovered": 6265
    }
  }
}