{
	"dataTime": "2023-05-24",
	"counter": {
		"dataTime": "2023-05-24",
		"confirmed": "31592429",
		"deaths": "34719",
		"recovered": "0"
	},
	"country": {
		"Nation-wide": {
			"confirmed": "31592429",
			"deaths": "34719",
			"recovered": "0"
		},
		"Seoul": {
			"confirmed": "6178627",
			"deaths": "6479",
			"recovered": "0"
		},
		"Busan": {
			"confirmed": "1861177",
			"deaths": "2851",
			"recovered": "0"
		},
		"Daegu": {
			"confirmed": "1371430",
			"deaths": "2012",
			"recovered": "0"
		},
		"Incheon": {
			"confirmed": "1837635",
			"deaths": "1921",
			"recovered": "0"
		},
		"Gwangju": {
			"confirmed": "920606",
			"deaths": "832",
			"recovered": "0"
		},
		"Daejeon": {
			"confirmed": "922445",
			"deaths": "960",
			"recovered": "0"
		},
		"Ulsan": {
			"confirmed": "667773",
			"deaths": "533",
			"recovered": "0"
		},
		"Sejong": {
			"confirmed": "251198",
			"deaths": "57",
			"recovered": "0"
		},
		"Gyeonggi-do": {
			"confirmed": "8554887",
			"deaths": "8443",
			"recovered": "0"
		},
		"Gangwon-do": {
			"confirmed": "925699",
			"deaths": "1339",
			"recovered": "0"
		},
		"Chungcheongbuk-do": {
			"confirmed": "990449",
			"deaths": "1052",
			"recovered": "0"
		},
		"Chungcheongnam-do": {
			"confirmed": "1277566",
			"deaths": "1602",
			"recovered": "0"
		},
		"Jeollabuk-do": {
			"confirmed": "1060840",
			"deaths": "1235",
			"recovered": "0"
		},
		"Jeollanam-do": {
			"confirmed": "1034134",
			"deaths": "1012",
			"recovered": "0"
		},
		"Gyeongsangbuk-do": {
			"confirmed": "1439188",
			"deaths": "2109",
			"recovered": "0"
		},
		"Gyeongsangnam-do": {
			"confirmed": "1879008",
			"deaths": "1984",
			"recovered": "0"
		},
		"Jeju": {
			"confirmed": "401392",
			"deaths": "282",
			"recovered": "0"
		},
		"Lazaretto": {
			"confirmed": "18375",
			"deaths": "16",
			"recovered": "0"
		}
	}
}