{
  "counter": {
    "dataTime": "2022-02-18",
    "daily": {
      "dataTime": "2022-02-18",
      "firstCnt": "8968",
      "secondCnt": "9818",
      "thirdCnt": "165994"
    },
    "yesterday": {
      "dataTime": "2022-02-17",
      "firstCnt": "44770186",
      "secondCnt": "44263131",
      "thirdCnt": "29902488"
    },
    "today": {
      "dataTime": "2022-02-18",
      "firstCnt": "44779154",
      "secondCnt": "44272949",
      "thirdCnt": "30068482"
    },
    "60세이상 접종률": {
      "firstCnt": "96.1",
      "secondCnt": "95.5",
      "thirdCnt": "87.4"
    }
  },
  "country": {
    "dataTime": "2022-02-18",
    "서울특별시": {
      "firstCnt": "1556",
      "firstTot": "8286542",
      "secondCnt": "1495",
      "secondTot": "8196392",
      "thirdCnt": "30743",
      "thirdTot": "5422466"
    },
    "부산광역시": {
      "firstCnt": "604",
      "firstTot": "2863877",
      "secondCnt": "540",
      "secondTot": "2830393",
      "thirdCnt": "10002",
      "thirdTot": "1918764"
    },
    "대구광역시": {
      "firstCnt": "442",
      "firstTot": "2009213",
      "secondCnt": "527",
      "secondTot": "1982096",
      "thirdCnt": "7370",
      "thirdTot": "1248929"
    },
    "인천광역시": {
      "firstCnt": "445",
      "firstTot": "2549533",
      "secondCnt": "565",
      "secondTot": "2521411",
      "thirdCnt": "8831",
      "thirdTot": "1711516"
    },
    "광주광역시": {
      "firstCnt": "202",
      "firstTot": "1254738",
      "secondCnt": "253",
      "secondTot": "1241298",
      "thirdCnt": "4414",
      "thirdTot": "869124"
    },
    "대전광역시": {
      "firstCnt": "257",
      "firstTot": "1238146",
      "secondCnt": "316",
      "secondTot": "1223991",
      "thirdCnt": "4980",
      "thirdTot": "806478"
    },
    "울산광역시": {
      "firstCnt": "213",
      "firstTot": "962674",
      "secondCnt": "259",
      "secondTot": "951688",
      "thirdCnt": "5762",
      "thirdTot": "631540"
    },
    "세종특별자치시": {
      "firstCnt": "99",
      "firstTot": "294082",
      "secondCnt": "82",
      "secondTot": "289500",
      "thirdCnt": "1317",
      "thirdTot": "181500"
    },
    "경기도": {
      "firstCnt": "2284",
      "firstTot": "11733169",
      "secondCnt": "2551",
      "secondTot": "11599197",
      "thirdCnt": "42318",
      "thirdTot": "7747788"
    },
    "강원도": {
      "firstCnt": "295",
      "firstTot": "1339427",
      "secondCnt": "275",
      "secondTot": "1326060",
      "thirdCnt": "4520",
      "thirdTot": "963091"
    },
    "충청북도": {
      "firstCnt": "287",
      "firstTot": "1417498",
      "secondCnt": "359",
      "secondTot": "1402403",
      "thirdCnt": "5754",
      "thirdTot": "989583"
    },
    "충청남도": {
      "firstCnt": "332",
      "firstTot": "1882452",
      "secondCnt": "450",
      "secondTot": "1861960",
      "thirdCnt": "6942",
      "thirdTot": "1325442"
    },
    "전라북도": {
      "firstCnt": "334",
      "firstTot": "1581578",
      "secondCnt": "307",
      "secondTot": "1566851",
      "thirdCnt": "5443",
      "thirdTot": "1165258"
    },
    "전라남도": {
      "firstCnt": "282",
      "firstTot": "1640630",
      "secondCnt": "338",
      "secondTot": "1624168",
      "thirdCnt": "5050",
      "thirdTot": "1244279"
    },
    "경상북도": {
      "firstCnt": "570",
      "firstTot": "2276606",
      "secondCnt": "672",
      "secondTot": "2247903",
      "thirdCnt": "8599",
      "thirdTot": "1550264"
    },
    "경상남도": {
      "firstCnt": "576",
      "firstTot": "2864241",
      "secondCnt": "668",
      "secondTot": "2829791",
      "thirdCnt": "11262",
      "thirdTot": "1911337"
    },
    "제주특별자치도": {
      "firstCnt": "190",
      "firstTot": "584748",
      "secondCnt": "161",
      "secondTot": "577847",
      "thirdCnt": "2687",
      "thirdTot": "381123"
    }
  }
}