{
	"dataTime": "2022-11-15",
	"daily": {
		"dataTime": "2022-11-15",
		"firstCnt": "188",
		"secondCnt": "221",
		"thirdCnt": "2149",
		"fourCnt": "1728",
		"winCnt": "88574",
		"vrate": "0%",
		"wrate": "0%"
	},
	"yesterday": {
		"dataTime": "2022-11-14",
		"firstCnt": "45124686",
		"secondCnt": "44695012",
		"thirdCnt": "33681852",
		"fourCnt": "7570289",
		"winCnt": "1539470",
		"vrate": "0%",
		"wrate": "0%"
	},
	"today": {
		"dataTime": "2022-11-15",
		"firstCnt": "45124874",
		"secondCnt": "44695233",
		"thirdCnt": "33684001",
		"fourCnt": "7572017",
		"winCnt": "1628044",
		"vrate": "87.1%",
		"wrate": "3.2%"
	}
}