{
	"dataTime": "2023-06-19",
	"daily": {
		"dataTime": "2023-06-19",
		"firstCnt": "135",
		"secondCnt": "193",
		"thirdCnt": "118",
		"fourCnt": "0",
		"winCnt": "2653",
		"vrate": "0%",
		"wrate": "0%"
	},
	"yesterday": {
		"dataTime": "2023-06-18",
		"firstCnt": "44761975",
		"secondCnt": "44350832",
		"thirdCnt": "33418941",
		"fourCnt": "7483962",
		"winCnt": "6711442",
		"vrate": "0%",
		"wrate": "0%"
	},
	"today": {
		"dataTime": "2023-06-19",
		"firstCnt": "44762110",
		"secondCnt": "44351025",
		"thirdCnt": "33419059",
		"fourCnt": "7483962",
		"winCnt": "6714095",
		"vrate": "86.7%",
		"wrate": "14.3%"
	}
}