{
	"dataTime": "2023-04-17",
	"서울특별시": {
		"firstCnt": "10",
		"firstTot": "8372603",
		"secondCnt": "12",
		"secondTot": "8296816",
		"thirdCnt": "0",
		"thirdTot": "6098038",
		"fourCnt": "0",
		"fourTot": "1260159",
		"winCnt": "613",
		"winTot": "1241254",
		"vrate": "87.8%",
		"wrate": "14.1%",
		"frate": "88.6%"
	},
	"부산광역시": {
		"firstCnt": "4",
		"firstTot": "2863370",
		"secondCnt": "8",
		"secondTot": "2835876",
		"thirdCnt": "0",
		"thirdTot": "2129385",
		"fourCnt": "0",
		"fourTot": "498429",
		"winCnt": "170",
		"winTot": "432468",
		"vrate": "85.3%",
		"wrate": "14%",
		"frate": "86.2%"
	},
	"대구광역시": {
		"firstCnt": "3",
		"firstTot": "2006481",
		"secondCnt": "5",
		"secondTot": "1984379",
		"thirdCnt": "0",
		"thirdTot": "1397264",
		"fourCnt": "0",
		"fourTot": "264772",
		"winCnt": "87",
		"winTot": "262472",
		"vrate": "83.7%",
		"wrate": "12%",
		"frate": "84.7%"
	},
	"인천광역시": {
		"firstCnt": "7",
		"firstTot": "2587955",
		"secondCnt": "3",
		"secondTot": "2564131",
		"thirdCnt": "0",
		"thirdTot": "1923399",
		"fourCnt": "0",
		"fourTot": "407038",
		"winCnt": "173",
		"winTot": "345555",
		"vrate": "86.4%",
		"wrate": "12.7%",
		"frate": "87.2%"
	},
	"광주광역시": {
		"firstCnt": "3",
		"firstTot": "1255594",
		"secondCnt": "3",
		"secondTot": "1244556",
		"thirdCnt": "0",
		"thirdTot": "963810",
		"fourCnt": "0",
		"fourTot": "239441",
		"winCnt": "49",
		"winTot": "178991",
		"vrate": "86.7%",
		"wrate": "13.6%",
		"frate": "87.4%"
	},
	"대전광역시": {
		"firstCnt": "1",
		"firstTot": "1242964",
		"secondCnt": "2",
		"secondTot": "1231115",
		"thirdCnt": "0",
		"thirdTot": "906948",
		"fourCnt": "0",
		"fourTot": "196767",
		"winCnt": "80",
		"winTot": "182137",
		"vrate": "84.9%",
		"wrate": "13.7%",
		"frate": "85.7%"
	},
	"울산광역시": {
		"firstCnt": "3",
		"firstTot": "963786",
		"secondCnt": "1",
		"secondTot": "954775",
		"thirdCnt": "0",
		"thirdTot": "717511",
		"fourCnt": "0",
		"fourTot": "138093",
		"winCnt": "60",
		"winTot": "127304",
		"vrate": "85.4%",
		"wrate": "12.5%",
		"frate": "86.2%"
	},
	"세종특별자치시": {
		"firstCnt": "1",
		"firstTot": "302240",
		"secondCnt": "0",
		"secondTot": "298558",
		"thirdCnt": "0",
		"thirdTot": "211870",
		"fourCnt": "0",
		"fourTot": "35434",
		"winCnt": "20",
		"winTot": "37524",
		"vrate": "78.6%",
		"wrate": "11.5%",
		"frate": "79.5%"
	},
	"경기도": {
		"firstCnt": "14",
		"firstTot": "11607982",
		"secondCnt": "19",
		"secondTot": "11500091",
		"thirdCnt": "0",
		"thirdTot": "8569766",
		"fourCnt": "0",
		"fourTot": "1729907",
		"winCnt": "795",
		"winTot": "1605152",
		"vrate": "86.5%",
		"wrate": "13.3%",
		"frate": "87.3%"
	},
	"강원도": {
		"firstCnt": "1",
		"firstTot": "1349444",
		"secondCnt": "0",
		"secondTot": "1338646",
		"thirdCnt": "0",
		"thirdTot": "1062400",
		"fourCnt": "0",
		"fourTot": "274133",
		"winCnt": "49",
		"winTot": "218614",
		"vrate": "87%",
		"wrate": "15.3%",
		"frate": "87.7%"
	},
	"충청북도": {
		"firstCnt": "2",
		"firstTot": "1426325",
		"secondCnt": "1",
		"secondTot": "1414334",
		"thirdCnt": "0",
		"thirdTot": "1103948",
		"fourCnt": "0",
		"fourTot": "281155",
		"winCnt": "131",
		"winTot": "232683",
		"vrate": "88.6%",
		"wrate": "15.8%",
		"frate": "89.4%"
	},
	"충청남도": {
		"firstCnt": "1",
		"firstTot": "1901644",
		"secondCnt": "2",
		"secondTot": "1884754",
		"thirdCnt": "0",
		"thirdTot": "1478045",
		"fourCnt": "0",
		"fourTot": "373589",
		"winCnt": "102",
		"winTot": "320280",
		"vrate": "88.7%",
		"wrate": "16.4%",
		"frate": "89.5%"
	},
	"전라북도": {
		"firstCnt": "0",
		"firstTot": "1570115",
		"secondCnt": "1",
		"secondTot": "1557982",
		"thirdCnt": "0",
		"thirdTot": "1268489",
		"fourCnt": "0",
		"fourTot": "373324",
		"winCnt": "76",
		"winTot": "297033",
		"vrate": "88.5%",
		"wrate": "18.2%",
		"frate": "89.2%"
	},
	"전라남도": {
		"firstCnt": "2",
		"firstTot": "1640548",
		"secondCnt": "0",
		"secondTot": "1627040",
		"thirdCnt": "0",
		"thirdTot": "1352282",
		"fourCnt": "0",
		"fourTot": "445170",
		"winCnt": "71",
		"winTot": "341386",
		"vrate": "89.4%",
		"wrate": "20.2%",
		"frate": "90.1%"
	},
	"경상북도": {
		"firstCnt": "2",
		"firstTot": "2275957",
		"secondCnt": "3",
		"secondTot": "2253197",
		"thirdCnt": "0",
		"thirdTot": "1714377",
		"fourCnt": "0",
		"fourTot": "401408",
		"winCnt": "103",
		"winTot": "372576",
		"vrate": "86.6%",
		"wrate": "15.4%",
		"frate": "87.5%"
	},
	"경상남도": {
		"firstCnt": "3",
		"firstTot": "2849256",
		"secondCnt": "7",
		"secondTot": "2821480",
		"thirdCnt": "0",
		"thirdTot": "2123470",
		"fourCnt": "0",
		"fourTot": "492718",
		"winCnt": "133",
		"winTot": "396753",
		"vrate": "86.2%",
		"wrate": "13.2%",
		"frate": "87%"
	},
	"제주특별자치도": {
		"firstCnt": "0",
		"firstTot": "591197",
		"secondCnt": "1",
		"secondTot": "585753",
		"thirdCnt": "0",
		"thirdTot": "438959",
		"fourCnt": "0",
		"fourTot": "94293",
		"winCnt": "28",
		"winTot": "87801",
		"vrate": "86.5%",
		"wrate": "14.3%",
		"frate": "87.3%"
	}
}