{
	"dataTime": "2022-10-30",
	"Nation-wide": {
		"confirmed": "25538799",
		"deaths": "29158",
		"recovered": "0"
	},
	"Seoul": {
		"confirmed": "4987483",
		"deaths": "5598",
		"recovered": "0"
	},
	"Busan": {
		"confirmed": "1509493",
		"deaths": "2500",
		"recovered": "0"
	},
	"Daegu": {
		"confirmed": "1115802",
		"deaths": "1690",
		"recovered": "0"
	},
	"Incheon": {
		"confirmed": "1474963",
		"deaths": "1564",
		"recovered": "0"
	},
	"Gwangju": {
		"confirmed": "748512",
		"deaths": "698",
		"recovered": "0"
	},
	"Daejeon": {
		"confirmed": "740552",
		"deaths": "796",
		"recovered": "0"
	},
	"Ulsan": {
		"confirmed": "547135",
		"deaths": "431",
		"recovered": "0"
	},
	"Sejong": {
		"confirmed": "200511",
		"deaths": "45",
		"recovered": "0"
	},
	"Gyeonggi-do": {
		"confirmed": "6875924",
		"deaths": "7296",
		"recovered": "0"
	},
	"Gangwon-do": {
		"confirmed": "754181",
		"deaths": "1090",
		"recovered": "0"
	},
	"Chungcheongbuk-do": {
		"confirmed": "800139",
		"deaths": "890",
		"recovered": "0"
	},
	"Chungcheongnam-do": {
		"confirmed": "1027152",
		"deaths": "1293",
		"recovered": "0"
	},
	"Jeollabuk-do": {
		"confirmed": "862753",
		"deaths": "1038",
		"recovered": "0"
	},
	"Jeollanam-do": {
		"confirmed": "842715",
		"deaths": "734",
		"recovered": "0"
	},
	"Gyeongsangbuk-do": {
		"confirmed": "1164041",
		"deaths": "1724",
		"recovered": "0"
	},
	"Gyeongsangnam-do": {
		"confirmed": "1533890",
		"deaths": "1535",
		"recovered": "0"
	},
	"Jeju": {
		"confirmed": "338989",
		"deaths": "220",
		"recovered": "0"
	},
	"Lazaretto": {
		"confirmed": "14564",
		"deaths": "16",
		"recovered": "0"
	}
}