{
	"Nation-wide": {
		"confirmed": "8250592",
		"deaths": "11481",
		"recovered": "2236770"
	},
	"Seoul": {
		"confirmed": "1812116",
		"deaths": "2927",
		"recovered": "414063"
	},
	"Busan": {
		"confirmed": "638008",
		"deaths": "924",
		"recovered": "111549"
	},
	"Daegu": {
		"confirmed": "324347",
		"deaths": "707",
		"recovered": "205676"
	},
	"Incheon": {
		"confirmed": "539517",
		"deaths": "714",
		"recovered": "143186"
	},
	"Gwangju": {
		"confirmed": "214679",
		"deaths": "214",
		"recovered": "14999"
	},
	"Daejeon": {
		"confirmed": "199846",
		"deaths": "322",
		"recovered": "59136"
	},
	"Ulsan": {
		"confirmed": "163623",
		"deaths": "139",
		"recovered": "100070"
	},
	"Sejong": {
		"confirmed": "50721",
		"deaths": "12",
		"recovered": "32369"
	},
	"Gyeonggi-do": {
		"confirmed": "2331981",
		"deaths": "3261",
		"recovered": "234668"
	},
	"Gangwon-do": {
		"confirmed": "189075",
		"deaths": "286",
		"recovered": "70011"
	},
	"Chungcheongbuk-do": {
		"confirmed": "209441",
		"deaths": "274",
		"recovered": "120789"
	},
	"Chungcheongnam-do": {
		"confirmed": "280561",
		"deaths": "379",
		"recovered": "100974"
	},
	"Jeollabuk-do": {
		"confirmed": "232558",
		"deaths": "314",
		"recovered": "142481"
	},
	"Jeollanam-do": {
		"confirmed": "199346",
		"deaths": "99",
		"recovered": "6965"
	},
	"Gyeongsangbuk-do": {
		"confirmed": "281039",
		"deaths": "495",
		"recovered": "147354"
	},
	"Gyeongsangnam-do": {
		"confirmed": "474251",
		"deaths": "350",
		"recovered": "255757"
	},
	"Jeju": {
		"confirmed": "99146",
		"deaths": "48",
		"recovered": "66937"
	},
	"Lazaretto": {
		"confirmed": "10337",
		"deaths": "16",
		"recovered": "9786"
	}
}