{
	"Nation-wide": {
		"confirmed": "3273449",
		"deaths": "8170",
		"recovered": "1166972"
	},
	"Seoul": {
		"confirmed": "804029",
		"deaths": "2432",
		"recovered": "303589"
	},
	"Busan": {
		"confirmed": "203763",
		"deaths": "472",
		"recovered": "66490"
	},
	"Daegu": {
		"confirmed": "136938",
		"deaths": "484",
		"recovered": "87703"
	},
	"Incheon": {
		"confirmed": "230798",
		"deaths": "442",
		"recovered": "85945"
	},
	"Gwangju": {
		"confirmed": "83040",
		"deaths": "121",
		"recovered": "14258"
	},
	"Daejeon": {
		"confirmed": "82149",
		"deaths": "232",
		"recovered": "29157"
	},
	"Ulsan": {
		"confirmed": "52562",
		"deaths": "91",
		"recovered": "33058"
	},
	"Sejong": {
		"confirmed": "18602",
		"deaths": "6",
		"recovered": "12002"
	},
	"Gyeonggi-do": {
		"confirmed": "979916",
		"deaths": "2514",
		"recovered": "231382"
	},
	"Gangwon-do": {
		"confirmed": "64362",
		"deaths": "160",
		"recovered": "30790"
	},
	"Chungcheongbuk-do": {
		"confirmed": "72008",
		"deaths": "163",
		"recovered": "44678"
	},
	"Chungcheongnam-do": {
		"confirmed": "107698",
		"deaths": "271",
		"recovered": "28956"
	},
	"Jeollabuk-do": {
		"confirmed": "80834",
		"deaths": "189",
		"recovered": "39182"
	},
	"Jeollanam-do": {
		"confirmed": "63450",
		"deaths": "60",
		"recovered": "6943"
	},
	"Gyeongsangbuk-do": {
		"confirmed": "102838",
		"deaths": "341",
		"recovered": "39122"
	},
	"Gyeongsangnam-do": {
		"confirmed": "148684",
		"deaths": "153",
		"recovered": "84965"
	},
	"Jeju": {
		"confirmed": "31969",
		"deaths": "23",
		"recovered": "19567"
	},
	"Lazaretto": {
		"confirmed": "9809",
		"deaths": "16",
		"recovered": "9185"
	}
}