{
	"Nation-wide": {
		"confirmed": "9936540",
		"deaths": "13141",
		"recovered": "3029904"
	},
	"Seoul": {
		"confirmed": "2148186",
		"deaths": "3144",
		"recovered": "480318"
	},
	"Busan": {
		"confirmed": "742457",
		"deaths": "1158",
		"recovered": "282459"
	},
	"Daegu": {
		"confirmed": "392298",
		"deaths": "783",
		"recovered": "259941"
	},
	"Incheon": {
		"confirmed": "634945",
		"deaths": "838",
		"recovered": "167661"
	},
	"Gwangju": {
		"confirmed": "267168",
		"deaths": "271",
		"recovered": "15090"
	},
	"Daejeon": {
		"confirmed": "251780",
		"deaths": "340",
		"recovered": "59220"
	},
	"Ulsan": {
		"confirmed": "199065",
		"deaths": "188",
		"recovered": "140460"
	},
	"Sejong": {
		"confirmed": "64613",
		"deaths": "14",
		"recovered": "42724"
	},
	"Gyeonggi-do": {
		"confirmed": "2788761",
		"deaths": "3609",
		"recovered": "439083"
	},
	"Gangwon-do": {
		"confirmed": "237251",
		"deaths": "344",
		"recovered": "92225"
	},
	"Chungcheongbuk-do": {
		"confirmed": "262002",
		"deaths": "344",
		"recovered": "164491"
	},
	"Chungcheongnam-do": {
		"confirmed": "346953",
		"deaths": "466",
		"recovered": "165990"
	},
	"Jeollabuk-do": {
		"confirmed": "283511",
		"deaths": "380",
		"recovered": "164593"
	},
	"Jeollanam-do": {
		"confirmed": "251499",
		"deaths": "140",
		"recovered": "6970"
	},
	"Gyeongsangbuk-do": {
		"confirmed": "351205",
		"deaths": "562",
		"recovered": "148289"
	},
	"Gyeongsangnam-do": {
		"confirmed": "581709",
		"deaths": "477",
		"recovered": "296516"
	},
	"Jeju": {
		"confirmed": "122662",
		"deaths": "67",
		"recovered": "94088"
	},
	"Lazaretto": {
		"confirmed": "10475",
		"deaths": "16",
		"recovered": "9786"
	}
}