{
	"Nation-wide": {
		"confirmed": "24413873",
		"deaths": "27867",
		"recovered": "0"
	},
	"Seoul": {
		"confirmed": "4761487",
		"deaths": "5400",
		"recovered": "0"
	},
	"Busan": {
		"confirmed": "1456840",
		"deaths": "2423",
		"recovered": "0"
	},
	"Daegu": {
		"confirmed": "1060968",
		"deaths": "1597",
		"recovered": "0"
	},
	"Incheon": {
		"confirmed": "1405904",
		"deaths": "1515",
		"recovered": "0"
	},
	"Gwangju": {
		"confirmed": "721625",
		"deaths": "643",
		"recovered": "0"
	},
	"Daejeon": {
		"confirmed": "707949",
		"deaths": "779",
		"recovered": "0"
	},
	"Ulsan": {
		"confirmed": "526796",
		"deaths": "406",
		"recovered": "0"
	},
	"Sejong": {
		"confirmed": "191189",
		"deaths": "43",
		"recovered": "0"
	},
	"Gyeonggi-do": {
		"confirmed": "6554660",
		"deaths": "7024",
		"recovered": "0"
	},
	"Gangwon-do": {
		"confirmed": "715017",
		"deaths": "1033",
		"recovered": "0"
	},
	"Chungcheongbuk-do": {
		"confirmed": "763692",
		"deaths": "839",
		"recovered": "0"
	},
	"Chungcheongnam-do": {
		"confirmed": "983626",
		"deaths": "1182",
		"recovered": "0"
	},
	"Jeollabuk-do": {
		"confirmed": "828474",
		"deaths": "981",
		"recovered": "0"
	},
	"Jeollanam-do": {
		"confirmed": "813064",
		"deaths": "667",
		"recovered": "0"
	},
	"Gyeongsangbuk-do": {
		"confirmed": "1102955",
		"deaths": "1622",
		"recovered": "0"
	},
	"Gyeongsangnam-do": {
		"confirmed": "1475124",
		"deaths": "1480",
		"recovered": "0"
	},
	"Jeju": {
		"confirmed": "331125",
		"deaths": "217",
		"recovered": "0"
	},
	"Lazaretto": {
		"confirmed": "13378",
		"deaths": "16",
		"recovered": "0"
	}
}