{
	"Nation-wide": {
		"confirmed": "30458857",
		"deaths": "33887",
		"recovered": "0"
	},
	"Seoul": {
		"confirmed": "5913863",
		"deaths": "6329",
		"recovered": "0"
	},
	"Busan": {
		"confirmed": "1814427",
		"deaths": "2800",
		"recovered": "0"
	},
	"Daegu": {
		"confirmed": "1331885",
		"deaths": "1971",
		"recovered": "0"
	},
	"Incheon": {
		"confirmed": "1769898",
		"deaths": "1868",
		"recovered": "0"
	},
	"Gwangju": {
		"confirmed": "887228",
		"deaths": "812",
		"recovered": "0"
	},
	"Daejeon": {
		"confirmed": "887763",
		"deaths": "933",
		"recovered": "0"
	},
	"Ulsan": {
		"confirmed": "653394",
		"deaths": "526",
		"recovered": "0"
	},
	"Sejong": {
		"confirmed": "241224",
		"deaths": "55",
		"recovered": "0"
	},
	"Gyeonggi-do": {
		"confirmed": "8232032",
		"deaths": "8319",
		"recovered": "0"
	},
	"Gangwon-do": {
		"confirmed": "896323",
		"deaths": "1302",
		"recovered": "0"
	},
	"Chungcheongbuk-do": {
		"confirmed": "955089",
		"deaths": "1020",
		"recovered": "0"
	},
	"Chungcheongnam-do": {
		"confirmed": "1232544",
		"deaths": "1549",
		"recovered": "0"
	},
	"Jeollabuk-do": {
		"confirmed": "1020767",
		"deaths": "1205",
		"recovered": "0"
	},
	"Jeollanam-do": {
		"confirmed": "996563",
		"deaths": "956",
		"recovered": "0"
	},
	"Gyeongsangbuk-do": {
		"confirmed": "1394932",
		"deaths": "2067",
		"recovered": "0"
	},
	"Gyeongsangnam-do": {
		"confirmed": "1828768",
		"deaths": "1893",
		"recovered": "0"
	},
	"Jeju": {
		"confirmed": "384654",
		"deaths": "266",
		"recovered": "0"
	},
	"Lazaretto": {
		"confirmed": "17503",
		"deaths": "16",
		"recovered": "0"
	}
}